vrt/__init__.py
vrt_generator-0.0.6.dist-info/METADATA
vrt_generator-0.0.6.dist-info/WHEEL
vrt_generator-0.0.6.dist-info/top_level.txt
vrt_generator-0.0.6.dist-info/RECORD
